itsh5py/__init__.py
itsh5py/config.py
itsh5py/hdf_support.py
itsh5py/queue_handler.py
itsh5py-0.7.2.dist-info/LICENSE.txt
itsh5py-0.7.2.dist-info/WHEEL
itsh5py-0.7.2.dist-info/METADATA
itsh5py-0.7.2.dist-info/RECORD
