Metadata-Version: 2.1
Name: itsh5py
Version: 0.7.2
Summary: Python datatype support for hdf files
Home-page: https://github.com/max3-2/itsh5py
License: MIT
Keywords: h5py, hdf, data storage
Author: Max Elfner <max_elfner@gmx.net>
Requires-Python: >=3.7
Classifier: Development Status :: 4 - Beta
Classifier: Programming Language :: Python :: 3
Classifier: Operating System :: Microsoft :: Windows
Classifier: Operating System :: POSIX :: Linux
Classifier: Operating System :: MacOS :: MacOS X
Classifier: Intended Audience :: Science/Research
Classifier: Natural Language :: English
Classifier: License :: OSI Approved :: MIT License
Requires-Dist: PyYAML > 5.4
Requires-Dist: pandas > 1.3
Requires-Dist: numpy > 1.19
Requires-Dist: h5py > 3.2
Requires-Dist: Sphinx ; extra == "doc"
Requires-Dist: Furo ; extra == "doc"
Requires-Dist: MyST-parser ; extra == "doc"
Project-URL: Documentation, https://itsh5py.readthedocs.io/en/latest/
Project-URL: Source, https://github.com/max3-2/itsh5py
Provides-Extra: doc
